github_gist/__init__.py
github_gist/id.py
jsfiddle_build/__init__.py
jsfiddle_build/__main__.py
jsfiddle_factory/__init__.py
jsfiddle_factory/__main__.py
jsfiddle_factory/build.py
jsfiddle_factory/detox.py
jsfiddle_factory/init.py
jsfiddle_factory/readme.py
jsfiddle_generator/__init__.py
jsfiddle_generator/gist.py
jsfiddle_generator/repo.py
jsfiddle_github/__init__.py
jsfiddle_github-2019.4.8.dist-info/METADATA
jsfiddle_github-2019.4.8.dist-info/WHEEL
jsfiddle_github-2019.4.8.dist-info/top_level.txt
jsfiddle_github-2019.4.8.dist-info/RECORD
