Metadata-Version: 2.1
Name: jsfiddle-github
Version: 2019.4.8
Summary: jsfiddle github integration helper
Home-page: https://github.com/looking-for-a-job/jsfiddle-github.py
License: UNKNOWN
Keywords: jsfiddle
Platform: UNKNOWN
Classifier: Operating System :: OS Independent
Classifier: Programming Language :: Python
Classifier: Programming Language :: Python :: 2
Classifier: Programming Language :: Python :: 2.7
Classifier: Programming Language :: Python :: 3
Classifier: Programming Language :: Python :: 3.4
Classifier: Programming Language :: Python :: 3.5
Classifier: Programming Language :: Python :: 3.6
Requires-Dist: github-gist
Requires-Dist: github-name
Requires-Dist: public
Requires-Dist: setuptools
